{
  "meta": {
    "title": "非营业货车_1-2吨_燃油",
    "filter": "客户类别 = '非营业货车' AND 吨位分段 = '1-2吨' AND (是否新能源 = false OR 是否新能源 IS NULL)",
    "years": [
      2021,
      2022,
      2023,
      2024,
      2025
    ],
    "compare": "full",
    "max_sign_date": "2026-03-31",
    "total_policies": 101763,
    "generated_at": "2026-04-02T09:30:12.428548"
  },
  "L0_identity": {
    "total_premium_wan": 11523.7,
    "total_policies": 101763,
    "years_covered": 5,
    "dominant_vehicle_type": "旧车转保",
    "dominant_vehicle_type_pct": 44.1
  },
  "L1_health": {
    "latest_year": {
      "year": 2025,
      "variable_cost_rate": 105.7,
      "variable_cost_light": "🔴",
      "margin_rate": -5.7,
      "loss_ratio": 94.2,
      "incident_rate": 15.8,
      "expense_ratio": 11.5,
      "earned_margin_wan": -42.8,
      "projected_margin_wan": -56.9,
      "policy_count": 9674,
      "avg_premium_yuan": 1064
    },
    "trend": {
      "margin_direction": "falling",
      "loss_ratio_direction": "falling",
      "worst_year": 2025,
      "worst_year_loss_ratio": 94.2
    },
    "alerts": [
      "🔴 2022年危险：变动成本率110.5%",
      "🔴 2023年危险：变动成本率108.1%",
      "🟡 2024年预警：变动成本率92.1%",
      "🔴 2025年危险：变动成本率105.7%"
    ]
  },
  "L2_deep": {
    "by_vehicle_type": {
      "旧车过户": {
        "variable_cost_rate": 101.1,
        "margin_wan": -33.0,
        "policy_count": 23970,
        "loss_ratio": 83.2,
        "expense_ratio": 17.9,
        "written_premium_wan": 3022.2
      },
      "旧车转保": {
        "variable_cost_rate": 114.1,
        "margin_wan": -672.4,
        "policy_count": 43743,
        "loss_ratio": 99.1,
        "expense_ratio": 15.0,
        "written_premium_wan": 4978.3
      },
      "新车": {
        "variable_cost_rate": 106.5,
        "margin_wan": -19.8,
        "policy_count": 2029,
        "loss_ratio": 87.4,
        "expense_ratio": 19.1,
        "written_premium_wan": 305.1
      },
      "旧车续保": {
        "variable_cost_rate": 85.5,
        "margin_wan": 468.1,
        "policy_count": 29529,
        "loss_ratio": 69.9,
        "expense_ratio": 15.6,
        "written_premium_wan": 3218.1
      }
    },
    "by_risk_grade": {
      "A": {
        "variable_cost_rate": 74.4,
        "margin_wan": 168.4,
        "policy_count": 7922,
        "loss_ratio": 62.8,
        "expense_ratio": 11.6,
        "written_premium_wan": 754.8
      },
      "B": {
        "variable_cost_rate": 99.8,
        "margin_wan": 1.2,
        "policy_count": 4844,
        "loss_ratio": 86.2,
        "expense_ratio": 13.6,
        "written_premium_wan": 512.9
      },
      "C": {
        "variable_cost_rate": 171.9,
        "margin_wan": -51.9,
        "policy_count": 705,
        "loss_ratio": 166.3,
        "expense_ratio": 5.6,
        "written_premium_wan": 77.6
      },
      "D": {
        "variable_cost_rate": 159.6,
        "margin_wan": -29.6,
        "policy_count": 512,
        "loss_ratio": 155.3,
        "expense_ratio": 4.3,
        "written_premium_wan": 58.8
      },
      "E": {
        "variable_cost_rate": 119.5,
        "margin_wan": -18.5,
        "policy_count": 1139,
        "loss_ratio": 116.2,
        "expense_ratio": 3.3,
        "written_premium_wan": 119.2
      },
      "X": {
        "variable_cost_rate": 141.3,
        "margin_wan": -25.2,
        "policy_count": 565,
        "loss_ratio": 130.0,
        "expense_ratio": 11.3,
        "written_premium_wan": 61.3
      },
      "无评分": {
        "variable_cost_rate": 103.1,
        "margin_wan": -310.2,
        "policy_count": 82837,
        "loss_ratio": 86.3,
        "expense_ratio": 16.8,
        "written_premium_wan": 9939.1
      }
    },
    "by_energy": {
      "非新-燃": {
        "variable_cost_rate": 102.2,
        "margin_wan": -255.9,
        "policy_count": 98524,
        "loss_ratio": 86.2,
        "expense_ratio": 16.0,
        "written_premium_wan": 11523.7
      },
      "非新-天": {
        "variable_cost_rate": 0,
        "margin_wan": 0,
        "policy_count": 0,
        "loss_ratio": 0,
        "expense_ratio": 0,
        "written_premium_wan": 0
      },
      "新能源": {
        "variable_cost_rate": 0,
        "margin_wan": 0,
        "policy_count": 0,
        "loss_ratio": 0,
        "expense_ratio": 0,
        "written_premium_wan": 0
      }
    },
    "by_year": {
      "2021": {
        "variable_cost_rate": 89.0,
        "margin_wan": 310.7,
        "policy_count": 24165,
        "loss_ratio": 71.6
      },
      "2022": {
        "variable_cost_rate": 110.5,
        "margin_wan": -453.9,
        "policy_count": 35038,
        "loss_ratio": 92.1
      },
      "2023": {
        "variable_cost_rate": 108.1,
        "margin_wan": -176.7,
        "policy_count": 19164,
        "loss_ratio": 93.7
      },
      "2024": {
        "variable_cost_rate": 92.1,
        "margin_wan": 95.5,
        "policy_count": 11238,
        "loss_ratio": 80.9
      },
      "2025": {
        "variable_cost_rate": 105.7,
        "margin_wan": -42.8,
        "policy_count": 9674,
        "loss_ratio": 94.2
      }
    }
  },
  "findings": [
    {
      "level": "🔴",
      "tag": "边际贡献转负",
      "text": "从2021年310.7万恶化至2025年-42.8万，整体亏损"
    },
    {
      "level": "🟡",
      "tag": "件均保费下降",
      "text": "1,194元→1,064元（-10.9%）"
    },
    {
      "level": "🔴",
      "tag": "赔付率显著恶化",
      "text": "71.6%→94.2%（+22.6pp）"
    },
    {
      "level": "🟡",
      "tag": "转保占比较高",
      "text": "43,743单（44%），需关注风险质量"
    },
    {
      "level": "🟡",
      "tag": "风险评分覆盖不足",
      "text": "82,837单（84%）无评分，精准定价受限"
    }
  ],
  "next_steps": [
    "提升风险评分覆盖率，优先对转保业务做风险分级",
    "按经代公司（952个）拆分对比变动成本率",
    "Top 业务员（403人）产能和质量排名"
  ]
}