{
  "stage": "原始数据",
  "timestamp": "2026-04-03T17:01:09.169868",
  "basic_stats": {
    "rows": 1169235,
    "columns": 42,
    "column_names": [
      "三级机构",
      "保单号",
      "批单号",
      "是否续保",
      "吨位分段",
      "缴费日期",
      "提核日期",
      "保险起期",
      "客户类别",
      "被保险人年龄分组",
      "新车购置价",
      "座位数",
      "初次登记年月",
      "是否过户车",
      "是否新车",
      "燃料种类",
      "是否新能源",
      "是否交商统保",
      "险别",
      "厂牌车型",
      "座位数.1",
      "车牌号码",
      "业务员",
      "代理人/经纪人",
      "客户源",
      "终端来源",
      "险类",
      "签单/批改保费",
      "商车自主定价系数",
      "批改类型",
      "车架号",
      "案件数",
      "赔款合计",
      "总费用金额",
      "车险分等级",
      "小货车评分",
      "大货车评分",
      "交叉销售标识-驾意",
      "交叉销售保费-驾意",
      "三者保额",
      "司机保额",
      "乘客险保额"
    ]
  },
  "field_quality": {
    "保单号": {
      "null_count": 0,
      "null_rate": 0.0,
      "unique_count": 1139234
    },
    "业务员": {
      "null_count": 0,
      "null_rate": 0.0,
      "unique_count": 386
    },
    "三级机构": {
      "null_count": 0,
      "null_rate": 0.0,
      "unique_count": 13
    },
    "保险起期": {
      "null_count": 0,
      "null_rate": 0.0,
      "unique_count": 1230
    },
    "险类": {
      "null_count": 0,
      "null_rate": 0.0,
      "unique_count": 2
    }
  }
}